musicdiff/__init__.py
musicdiff/__main__.py
musicdiff/annotation.py
musicdiff/comparison.py
musicdiff/detaillevel.py
musicdiff/m21utils.py
musicdiff/py.typed
musicdiff/visualization.py
musicdiff-5.1.dist-info/licenses/LICENSE
musicdiff-5.1.dist-info/METADATA
musicdiff-5.1.dist-info/WHEEL
musicdiff-5.1.dist-info/top_level.txt
musicdiff-5.1.dist-info/RECORD
