Metadata-Version: 2.4
Name: musicdiff
Version: 5.1
Summary: A music score notation diff package
Home-page: https://github.com/gregchapman-dev/musicdiff
Author: Greg Chapman
Author-email: gregc@mac.com
Project-URL: Documentation, https://gregchapman-dev.github.io/musicdiff
Project-URL: Source, https://github.com/gregchapman-dev/musicdiff
Project-URL: Bug Reports, https://github.com/gregchapman-dev/musicdiff/issues
Keywords: music,score,notation,diff,compare,comparison,OMR,Optical Music Recognition,assess,assessment,evaluation,training,music21,OMR-NED
Classifier: Development Status :: 5 - Production/Stable
Classifier: License :: OSI Approved :: MIT License
Classifier: Programming Language :: Python :: 3 :: Only
Classifier: Operating System :: OS Independent
Classifier: Natural Language :: English
Requires-Python: >=3.10
License-File: LICENSE
Requires-Dist: music21>=9.9.1
Requires-Dist: numpy
Requires-Dist: converter21>=4.0
Dynamic: author
Dynamic: author-email
Dynamic: classifier
Dynamic: description
Dynamic: description-content-type
Dynamic: home-page
Dynamic: keywords
Dynamic: license-file
Dynamic: project-url
Dynamic: requires-dist
Dynamic: requires-python
Dynamic: summary
